loadmemory/__init__.py
loadmemory/db/__init__.py
loadmemory/db/tiny_db.py
loadmemory/excel/__init__.py
loadmemory/utils/__init__.py
loadmemory/utils/configparser.py
loadmemory/utils/time_util.py
loadmemory-0.2.0.dist-info/METADATA
loadmemory-0.2.0.dist-info/WHEEL
loadmemory-0.2.0.dist-info/top_level.txt
loadmemory-0.2.0.dist-info/RECORD
