Metadata-Version: 2.4
Name: loadmemory
Version: 0.2.0
Summary: Utilities for loadmemory
Home-page: https://github.com/zhouwe1/loadmemory_util
Author: zhouwe1
Author-email: zhouwe1 <zhouwei@live.it>
License: MIT
Requires-Python: >=3.10
Provides-Extra: excel
Requires-Dist: openpyxl>=3.0; extra == "excel"
Provides-Extra: db
Requires-Dist: tinydb>=4.0; extra == "db"
Dynamic: author
Dynamic: home-page
Dynamic: requires-python
